{"1":["psalms 120:1","jeremiah 3:23","psalms 87:1","psalms 68:15-16","psalms 78:68","psalms 2:6","isaiah 2:3","psalms 123:1"],"2":["psalms 146:5-6","psalms 124:8","jeremiah 20:11","psalms 46:1","psalms 115:15","isaiah 40:28-29","isaiah 41:13","hebrews 13:6","hosea 13:9"],"3":["psalms 91:12","psalms 41:2","1peter 1:5","psalms 66:9","1samuel 2:9","proverbs 2:8","proverbs 3:23","isaiah 27:3","psalms 127:1","proverbs 3:26"],"4":["psalms 127:1","psalms 27:1","isaiah 27:3","ecclesiastes 8:16","revelation 7:15","1kings 18:27","psalms 32:7-8"],"5":["matthew 23:37","isaiah 4:5-6","psalms 91:1","psalms 109:31","isaiah 32:2","exodus 13:21","isaiah 25:4","psalms 16:8"],"6":["psalms 91:5-10","isaiah 49:10","revelation 7:16","jonah 4:8"],"7":["romans 8:28","matthew 6:13","psalms 97:10","proverbs 12:21","romans 8:35-39","psalms 91:9-12","psalms 41:2","job 5:19-27","psalms 34:22","2timothy 4:18","psalms 145:20"],"8":["deuteronomy 28:19","2samuel 5:2","ezra 8:21","ezra 8:31","deuteronomy 28:6","proverbs 2:8","proverbs 3:6","james 4:13-16","psalms 115:18","psalms 113:2"]}