{"1":["lamentations 5:20","psalms 74:1","psalms 35:17","psalms 10:12","psalms 22:1-2","job 13:24","psalms 90:14","psalms 80:4","psalms 6:3","psalms 94:3-4","isaiah 59:2","psalms 89:46","deuteronomy 31:17","psalms 44:24","psalms 85:5"],"2":["psalms 44:14-16","lamentations 1:9","ecclesiastes 5:17","psalms 17:9","psalms 123:3-4","job 10:15","1samuel 24:19","psalms 42:4","john 16:6","psalms 31:18","matthew 26:38","micah 7:8-10","psalms 9:6","psalms 94:18-19","jeremiah 8:18","esther 7:6","job 7:12-15","job 9:19-21","psalms 74:10","luke 22:53","psalms 77:2-12","psalms 143:3-4","nehemiah 2:2","job 9:27-28","psalms 7:4-5","psalms 42:9-10","psalms 74:18","philippians 2:27","1samuel 18:29","jeremiah 45:3","psalms 22:7-8","romans 9:2","psalms 38:17","job 23:8-10","lamentations 1:5","psalms 8:2","jeremiah 15:18","psalms 142:4-7","psalms 116:3","proverbs 15:13","psalms 10:18","psalms 7:2"],"3":["jeremiah 51:39","psalms 9:13","ephesians 5:14","psalms 31:7","1samuel 14:29","psalms 5:1","revelation 21:23","lamentations 5:1","1samuel 14:27","psalms 18:28","psalms 25:19","psalms 119:153","jeremiah 51:57","ezra 9:8","luke 2:32"],"4":["ezekiel 35:12-15","psalms 25:2","psalms 62:6","lamentations 1:16","proverbs 12:3","psalms 35:19","psalms 55:22","jeremiah 1:19","psalms 112:6","psalms 38:16","joshua 7:9","psalms 121:1-3","psalms 10:11","psalms 35:25","psalms 62:2","psalms 9:19"],"5":["psalms 147:11","psalms 119:81","1samuel 2:1","luke 2:20","psalms 36:7","psalms 33:21-22","habakkuk 3:18","isaiah 12:2","psalms 9:14","luke 1:47","psalms 33:18","psalms 51:12","psalms 43:4-5","jude 1:21","psalms 32:10","psalms 52:8"],"6":["psalms 116:7","psalms 119:7","psalms 21:13"]}