{"1":["psalms 95:3","psalms 111:1","1corinthians 14:15","john 10:34-36","ephesians 5:19","exodus 22:28","psalms 103:1-2","psalms 82:6","hebrews 1:14","acts 23:5","psalms 86:12-13","psalms 9:1","psalms 119:46","psalms 96:4","psalms 82:1"],"2":["psalms 56:10","psalms 85:10","psalms 99:5","psalms 28:2","psalms 89:1-2","micah 7:18-20","matthew 24:35","psalms 100:4-5","psalms 36:5-6","romans 15:8-9","psalms 115:1","john 1:17","psalms 99:9","matthew 5:18","john 10:35","daniel 6:10","luke 1:68-72","1kings 8:29-30","isaiah 63:7","isaiah 42:21","psalms 86:15","psalms 56:4","psalms 5:7"],"3":["psalms 63:8","2corinthians 12:8-10","ephesians 6:10","psalms 34:4-6","psalms 77:1-2","1peter 5:10","isaiah 41:10","colossians 1:11","psalms 18:6","ephesians 3:16","psalms 29:11","isaiah 12:2","psalms 28:7","isaiah 65:24","isaiah 40:29-31","philippians 4:13","psalms 27:14","zechariah 10:12"],"4":["isaiah 49:23","psalms 51:13","psalms 102:22","psalms 22:27","psalms 22:22","isaiah 60:16","psalms 102:15","psalms 72:11","isaiah 60:3-5","psalms 69:30-32","psalms 71:18","revelation 21:24","revelation 11:15"],"5":["luke 19:37-38","ephesians 1:12","revelation 5:12-14","isaiah 52:7-10","revelation 19:1","malachi 1:11","jeremiah 31:11-12","exodus 33:18-19","matthew 21:5-9","isaiah 66:10-14","psalms 21:5","revelation 7:12","2corinthians 4:6","isaiah 65:14","zephaniah 3:14-15","revelation 4:11","john 13:31-32","john 17:1","exodus 15:11","isaiah 6:1-3","ephesians 1:6"],"6":["isaiah 66:2","isaiah 57:15","daniel 5:20-24","proverbs 3:34","ezekiel 28:2-9","luke 1:48","psalms 51:17","psalms 113:5-6","exodus 18:11","matthew 25:41","luke 18:14","james 4:6","daniel 4:37","isaiah 2:17","luke 14:11","1peter 5:5-6","psalms 139:2","2thessalonians 1:9","isaiah 2:11","acts 12:22-23","1samuel 2:7-8","luke 1:51-53","job 40:11-12"],"7":["psalms 56:1-2","psalms 20:6","psalms 60:5","isaiah 9:12","acts 2:33","psalms 56:9","psalms 66:10-12","psalms 71:20-21","jeremiah 51:25","isaiah 57:16","psalms 17:7","isaiah 5:25","psalms 119:49-50","psalms 41:7-8","isaiah 41:10","job 19:25-26","psalms 44:3","psalms 18:35","isaiah 10:4","psalms 77:10","job 13:15","isaiah 9:21","psalms 23:3-4","psalms 44:5-7","psalms 85:6","psalms 35:1-3","psalms 64:7-8","isaiah 9:17","micah 7:8-10","psalms 144:1-2"],"8":["psalms 136:1","jude 1:1","jeremiah 32:39-40","psalms 71:6-9","philippians 1:6","psalms 71:17-18","romans 5:10","job 10:3","psalms 103:17","psalms 57:2","romans 8:28-30","isaiah 43:21","john 15:2","1peter 1:3-5","psalms 100:5","1thessalonians 5:24","1peter 4:19","job 10:8","isaiah 42:16","isaiah 26:12","job 14:15","psalms 100:3"]}