{"1":["psalms 98:4-6","psalms 93:1","isaiah 11:11","psalms 99:1","isaiah 49:13","isaiah 24:14-16","psalms 96:10-11","isaiah 49:1","psalms 2:11","matthew 6:13","isaiah 41:5","zephaniah 2:11","revelation 11:17","matthew 3:3","isaiah 51:5","isaiah 42:4","mark 11:10","colossians 1:13","isaiah 66:19","isaiah 60:9","obadiah 1:21","matthew 6:10","isaiah 42:10-12","genesis 10:5","luke 2:10-11"],"2":["genesis 18:25","exodus 20:21","psalms 99:4","exodus 24:16-18","nahum 1:3","psalms 77:19","proverbs 16:12","romans 11:33","exodus 19:9","1kings 8:10-12","hebrews 1:8-9","psalms 89:14","psalms 18:11-12","psalms 45:6-7","deuteronomy 4:11-12"],"3":["hebrews 12:29","psalms 50:3","habakkuk 3:5","deuteronomy 32:22","revelation 20:15","nahum 1:5-6","deuteronomy 4:11","2peter 3:10-12","deuteronomy 5:23-24","malachi 4:1","daniel 7:10","2thessalonians 1:8","psalms 18:8","deuteronomy 4:36","deuteronomy 5:4","revelation 11:5","psalms 21:8-9"],"4":["matthew 28:2-3","psalms 77:18","psalms 144:5-6","revelation 19:11","revelation 11:19","matthew 27:50-51","jeremiah 10:10","psalms 114:7","job 9:6","exodus 19:16-18","psalms 104:32","psalms 96:9"],"5":["psalms 47:2","isaiah 54:5","zechariah 4:14","joshua 3:11","habakkuk 3:6","isaiah 24:19-20","1corinthians 1:2","micah 4:13","judges 5:4-5","psalms 83:18","psalms 46:6","micah 1:3-4","nahum 1:5","mark 11:3","isaiah 64:1-2"],"6":["psalms 89:2","isaiah 60:2-3","psalms 67:4","psalms 89:5","isaiah 66:18","2samuel 22:47","psalms 19:1","psalms 50:6","isaiah 45:6","numbers 14:21","matthew 6:9","habakkuk 2:14","isaiah 40:5","psalms 98:3","psalms 36:5-6","revelation 19:2","isaiah 6:3","isaiah 1:2"],"7":["1peter 1:12","revelation 14:8-10","exodus 20:4","revelation 5:11-14","isaiah 42:17","jeremiah 10:14","hebrews 1:6","2chronicles 3:13","deuteronomy 27:15","isaiah 41:29","deuteronomy 5:8","isaiah 44:9-11","isaiah 37:18-19","exodus 25:20","leviticus 26:1"],"8":["psalms 52:6","psalms 58:10","revelation 18:20","revelation 19:1-7","matthew 21:4-9","isaiah 52:7-10","psalms 48:11","isaiah 62:11","isaiah 51:3","zechariah 9:9","zephaniah 3:14-17"],"9":["psalms 95:3","psalms 96:4","jeremiah 10:10","psalms 115:3-8","philippians 2:9-11","ephesians 1:21","psalms 83:18","exodus 18:11","psalms 135:5","jeremiah 10:8"],"10":["romans 7:15","psalms 34:14","psalms 36:4","proverbs 2:8","2thessalonians 3:2","1peter 1:8","isaiah 45:17","1john 5:2-3","john 20:28-30","proverbs 3:7","james 1:12","revelation 13:8","psalms 101:3","psalms 119:104","1corinthians 8:3","psalms 119:163","daniel 6:22","romans 8:28-30","proverbs 8:13","1peter 1:5","psalms 145:20","psalms 125:3","jeremiah 15:21","2thessalonians 2:8-12","daniel 6:27","1john 4:19","psalms 37:39-40","romans 7:24","daniel 3:28","james 2:5","1john 5:18","amos 5:15","psalms 91:14","romans 12:9","psalms 31:23","psalms 37:27-28"],"11":["micah 7:9","revelation 22:5","esther 8:16","psalms 18:28","isaiah 60:1-2","psalms 112:4","job 22:28","psalms 126:5-6","proverbs 4:18","isaiah 62:1","james 5:7-11","revelation 21:23","john 12:46","galatians 6:8"],"12":["zephaniah 3:14-17","psalms 60:6","habakkuk 3:17-18","philippians 4:4","habakkuk 1:12-13","psalms 32:11-1","psalms 30:4","hebrews 12:10"]}