{"1":["1corinthians 4:16","ephesians 5:1-2","hebrews 6:12","1corinthians 10:33","philippians 3:17","2thessalonians 3:9","1thessalonians 1:6","philippians 2:4-5","romans 15:2-3"],"2":["1corinthians 11:17","1corinthians 11:22","2thessalonians 3:6","proverbs 31:28-31","luke 1:6","1corinthians 15:2","1corinthians 4:17","1thessalonians 4:1-2","1corinthians 7:17","1thessalonians 3:6","2thessalonians 2:15"],"3":["philippians 2:7-11","1timothy 2:11-12","matthew 28:18","john 5:20-30","ephesians 4:15","isaiah 49:3-6","isaiah 55:4","john 17:2-5","genesis 3:16","colossians 2:19","colossians 1:18","isaiah 52:13","colossians 2:10","ephesians 1:20-23","colossians 3:18","isaiah 61:1-4","john 3:34-36","john 14:28","1corinthians 3:23","1peter 3:5-6","1peter 3:1","1corinthians 15:27-28","ephesians 5:22-24"],"4":["1corinthians 11:14","2samuel 19:4","1corinthians 14:1-25","1corinthians 12:28","1corinthians 12:10","2samuel 15:30"],"5":["1corinthians 14:34","deuteronomy 21:12","luke 2:36","acts 21:9","acts 2:17"],"6":["numbers 5:18","deuteronomy 22:5"],"7":["1corinthians 11:3","genesis 3:16","james 3:9","genesis 5:1","genesis 1:26-27","psalms 8:6","genesis 9:6"],"8":["1timothy 2:13","genesis 2:21-23"],"9":["genesis 2:18","genesis 2:20","genesis 2:23-24"],"10":["genesis 20:16","genesis 24:64-65","ecclesiastes 5:6","hebrews 1:14","matthew 18:10"],"11":["1corinthians 12:12-22","galatians 3:28","1corinthians 7:10-14"],"12":["hebrews 1:2-3","proverbs 16:4","1corinthians 8:6","romans 11:36"],"13":["1corinthians 10:15","luke 12:57","john 7:24"],"14":["1corinthians 14:35","2samuel 14:26"],"16":["1corinthians 14:33-34","1corinthians 16:1","acts 21:21","1corinthians 7:17","acts 21:24","1timothy 6:3-4","1thessalonians 2:14"],"17":["hebrews 10:25","isaiah 1:13-14","leviticus 19:17","jeremiah 7:9-10","1corinthians 11:2","romans 13:3","1corinthians 14:26","proverbs 27:5","1corinthians 14:23","1peter 2:14","1corinthians 11:34","1corinthians 11:20","isaiah 58:1-4","1corinthians 11:22"],"18":["1corinthians 1:10-12","1corinthians 5:1","1corinthians 6:1","1corinthians 3:3"],"19":["acts 26:5","titus 3:10","acts 15:5","acts 20:30","galatians 5:20","luke 2:35","2peter 2:1-2","matthew 18:7","acts 28:22","2corinthians 13:5-7","acts 24:5","1john 2:19","acts 5:17","luke 17:1","deuteronomy 13:3","acts 24:14","1timothy 4:1-2"],"21":["2peter 2:13","1corinthians 10:16-18","1corinthians 11:23-25","jude 1:12"],"22":["1timothy 3:15","1corinthians 10:32","acts 20:28","1timothy 3:5","1corinthians 11:17","proverbs 17:5","1corinthians 11:2","1corinthians 15:9","james 2:5-6"],"23":["matthew 26:2","1corinthians 15:3","galatians 1:11-12","matthew 28:20","matthew 26:34","luke 22:19-20","1thessalonians 4:2","acts 20:7","matthew 26:26-28","1corinthians 11:23-25","mark 14:22-24","matthew 26:17","deuteronomy 4:5","galatians 1:1"],"24":["1corinthians 11:27-28","songofsolomon 5:1","matthew 26:13","psalms 22:29","psalms 22:26","isaiah 55:1-3","songofsolomon 1:4","exodus 12:14","john 6:53-58","psalms 111:4","isaiah 26:8","1corinthians 10:3-4","joshua 4:7","1corinthians 5:7-8","proverbs 9:5","isaiah 25:6","1corinthians 10:16-17"],"25":["luke 22:20","1corinthians 11:27-28","hebrews 9:15-20","hebrews 13:20","2corinthians 3:14","2corinthians 3:6","1corinthians 10:16"],"26":["john 21:22","1corinthians 4:5","1john 2:28","revelation 22:20","hebrews 9:28","2thessalonians 2:2-3","acts 1:11","revelation 20:11-12","revelation 1:7","2thessalonians 1:10","2peter 3:10","jude 1:14","john 14:3","1thessalonians 4:16","1corinthians 15:23"],"27":["1corinthians 10:21","john 13:18-27","2chronicles 30:18-20","leviticus 10:1-3","numbers 9:13","matthew 22:11","hebrews 10:29","numbers 9:10","john 6:63-64","john 6:51"],"28":["1john 3:20-21","zechariah 7:5-7","matthew 5:23-24","psalms 26:2-7","numbers 9:10-13","haggai 1:5","lamentations 3:40","2corinthians 13:5","haggai 1:7","galatians 6:4","1corinthians 11:31"],"29":["james 5:12","romans 13:2","1corinthians 11:30","ecclesiastes 8:5","hebrews 5:14","1corinthians 11:24","1corinthians 11:27","james 3:1","1corinthians 11:32-34"],"30":["1kings 13:21-24","1thessalonians 4:14","numbers 20:24","1corinthians 11:32","psalms 38:1-8","amos 3:2","2samuel 12:14-18","numbers 20:12","revelation 3:19","acts 13:36","hebrews 12:5-11","psalms 78:30-31","1corinthians 15:51","exodus 15:26","psalms 89:31-34","numbers 21:6-9"],"31":["revelation 3:2-3","psalms 32:3-5","revelation 2:5","luke 15:18-20","1john 1:9","jeremiah 31:18-20","1corinthians 11:28"],"32":["deuteronomy 8:5","job 33:18-30","job 5:17-18","psalms 94:12-13","zephaniah 3:2","hebrews 12:5-11","revelation 3:19","1john 5:19","psalms 118:18","proverbs 3:11-12","job 34:31-32","isaiah 1:5","jeremiah 7:28","romans 3:19","1corinthians 11:30"],"34":["1corinthians 7:17","1corinthians 16:5","1corinthians 16:2","1corinthians 11:21-22","1corinthians 4:19","titus 1:5"]}