{"1":["genesis 6:2","proverbs 6:25","proverbs 4:25","2samuel 11:2-4","proverbs 23:31-33","psalms 119:37","1john 2:16","matthew 5:28-29","james 1:14-15"],"2":["job 20:29","job 27:13","hebrews 13:4"],"3":["job 21:30","job 34:22","proverbs 10:29","matthew 7:13","psalms 73:18","jude 1:7","proverbs 1:27","proverbs 21:15","romans 9:22","isaiah 28:21","2thessalonians 1:9","1thessalonians 5:3","2peter 2:1","psalms 55:23"],"4":["psalms 44:21","job 14:16","john 1:48","proverbs 15:3","job 34:21","genesis 16:13","hebrews 4:13","2chronicles 16:9","proverbs 5:21","jeremiah 32:19","psalms 139:1-3","jeremiah 16:17"],"5":["proverbs 12:11","psalms 7:3-5","micah 2:11","psalms 4:2","psalms 12:2","psalms 44:20-21","ezekiel 13:8","jeremiah 2:5"],"6":["proverbs 16:11","job 6:2","joshua 22:22","psalms 26:1","psalms 1:6","2timothy 2:19","psalms 17:2-3","matthew 7:23","job 27:5-6","psalms 139:23","isaiah 26:7","psalms 7:8-9","daniel 5:27","1samuel 2:3","micah 6:11"],"7":["job 9:30","numbers 15:39","isaiah 33:15","ezekiel 14:7","ezekiel 14:3","psalms 101:3","matthew 5:29","ecclesiastes 11:9","psalms 44:20-21","job 23:11","ezekiel 6:9"],"8":["judges 6:3-6","leviticus 26:16","job 18:19","deuteronomy 28:38","micah 6:15","deuteronomy 28:30-33","deuteronomy 28:51","job 24:6","psalms 109:13","job 15:30","job 20:18","job 5:4-5"],"9":["proverbs 7:21","proverbs 2:16-19","1kings 11:4","judges 16:5","proverbs 6:25","job 24:15-16","proverbs 5:3-23","ecclesiastes 7:26","proverbs 22:14","hosea 7:4","jeremiah 5:8","nehemiah 13:26"],"10":["isaiah 47:2","deuteronomy 28:30","2samuel 12:11","jeremiah 8:10","exodus 11:5","hosea 4:13-14","matthew 24:41"],"11":["genesis 20:9","leviticus 20:10","ezekiel 16:38","genesis 38:24","job 31:28","genesis 26:10","deuteronomy 22:22-24","genesis 39:9","exodus 20:14","proverbs 6:29-33"],"12":["proverbs 6:27","job 20:28","hebrews 13:4","job 15:30","malachi 3:5","proverbs 3:33","job 26:6","jeremiah 5:7-9"],"13":["ephesians 6:9","deuteronomy 24:14-15","exodus 21:26-27","exodus 21:20-21","colossians 4:1","leviticus 25:43","jeremiah 34:14-17","leviticus 25:46","deuteronomy 15:12-15"],"14":["micah 7:4","psalms 7:6","job 10:2","james 2:13","psalms 9:19","mark 7:2","psalms 76:9","hosea 9:7","isaiah 10:3","psalms 44:21","romans 3:19","job 9:32","psalms 10:12-15","psalms 9:12","zechariah 2:13","psalms 143:2"],"15":["isaiah 58:7","job 10:3","job 10:8-12","job 34:19","proverbs 14:31","malachi 2:10","psalms 139:14-16","nehemiah 5:5","proverbs 22:2"],"16":["deuteronomy 15:7-10","isaiah 38:14","psalms 119:82","luke 16:21","job 5:16","psalms 119:123","acts 11:29","psalms 69:3","job 22:7-9","psalms 112:9","deuteronomy 28:32","galatians 2:10","lamentations 4:17","job 20:19"],"17":["ezekiel 18:7","ezekiel 18:16","deuteronomy 15:14","deuteronomy 15:11","romans 12:13","nehemiah 8:10","job 22:7","1john 3:17","john 13:29","job 29:12-16","luke 11:41","james 1:27","acts 4:32"],"19":["job 22:6","job 24:4","james 2:16","acts 9:39","luke 3:11","isaiah 58:7","job 29:13","2chronicles 28:15","matthew 25:43","1john 3:18","matthew 25:36"],"20":["job 29:11","deuteronomy 24:13"],"21":["proverbs 23:10-11","jeremiah 5:28","job 6:27","job 22:9","micah 2:1-2","job 29:12","micah 7:3","ezekiel 22:7","job 24:9"],"22":["psalms 7:4-5","job 31:40","joshua 22:22-23","psalms 137:6","job 31:10","job 38:15"],"23":["2corinthians 5:11","genesis 39:9","job 42:5-6","psalms 119:120","psalms 76:7","job 21:20","joel 1:15","job 20:23","job 40:9","isaiah 13:6","job 13:11"],"24":["deuteronomy 8:12-14","proverbs 30:9","genesis 31:1","colossians 3:5","1timothy 6:10","luke 12:15","proverbs 11:28","psalms 52:7","mark 10:24-25","psalms 49:17","1timothy 6:17","psalms 62:10","proverbs 10:15","psalms 49:6-7"],"25":["hosea 12:8","daniel 4:30","habakkuk 1:16","jeremiah 9:23","luke 12:19","esther 5:11","luke 16:19","psalms 62:10","proverbs 23:5","isaiah 10:13-14","ezekiel 28:5","luke 16:25","deuteronomy 8:17-18"],"26":["ezekiel 8:16","psalms 8:3-4","2kings 23:11","2kings 23:5","deuteronomy 4:19","genesis 1:16-18","deuteronomy 11:16","jeremiah 8:2","deuteronomy 17:3","jeremiah 44:17"],"27":["deuteronomy 11:16","1kings 19:18","deuteronomy 13:6","isaiah 44:20","psalms 2:12","romans 1:28","hosea 13:2","romans 1:21"],"28":["joshua 24:27","psalms 50:6","jude 1:4","proverbs 30:9","1john 2:23","deuteronomy 17:2-7","judges 11:27","genesis 18:25","job 9:15","hebrews 12:23","job 23:7","2peter 2:1","job 31:11","titus 1:16","joshua 24:23","deuteronomy 17:9"],"29":["psalms 35:25-26","psalms 35:13-14","2samuel 1:12","2samuel 4:10-11","2samuel 16:5-8","obadiah 1:12","proverbs 24:17-18","proverbs 17:5"],"30":["exodus 23:4-5","matthew 5:22","matthew 5:43-44","1peter 2:22-23","ecclesiastes 5:6","romans 12:14","matthew 12:36","ecclesiastes 5:2","james 3:6","james 3:9-10","1peter 3:9"],"31":["jeremiah 40:15-16","2samuel 19:21-22","1samuel 26:8","job 22:7","job 19:22","psalms 35:25","proverbs 1:11-12","2samuel 16:9-10","1samuel 24:4","luke 22:50-51","luke 9:54-55","micah 3:2-3","psalms 27:2","proverbs 1:18","1samuel 24:10"],"32":["genesis 19:2-3","job 31:17-18","judges 19:15","matthew 25:40","1timothy 5:10","romans 12:13","matthew 25:35","matthew 25:44-45","isaiah 58:7","judges 19:20-21","hebrews 13:2","1peter 4:9"],"33":["genesis 3:7-8","acts 5:8","hosea 6:7","1john 1:8-10","joshua 7:11","proverbs 28:13","genesis 3:12"],"34":["2corinthians 5:16","proverbs 29:25","proverbs 24:11-12","jeremiah 38:16","exodus 32:27","nehemiah 13:4-8","jeremiah 38:4-5","matthew 27:20-26","nehemiah 5:7","micah 7:3","nehemiah 13:28","exodus 23:2","numbers 25:14-15","job 34:19","job 22:8","esther 4:11","esther 4:14","amos 5:11-13","jeremiah 38:19"],"35":["job 38:1-3","job 13:24","job 33:10-11","job 19:23-24","job 40:4-5","job 35:14","job 30:28","job 23:3-7","matthew 5:25","job 19:7","job 33:6","job 13:21-22","job 13:3","job 19:11","job 27:7","job 17:3","psalms 26:1"],"36":["philippians 4:1","job 29:14","exodus 28:12","isaiah 62:3","isaiah 22:22"],"37":["job 42:3-6","job 13:15","job 14:16","1john 3:19-21","job 9:3","hebrews 4:15-16","job 1:3","genesis 32:28","psalms 19:12","ephesians 3:12","job 29:25"],"38":["psalms 65:13","job 20:27","james 5:4","habakkuk 2:11"],"39":["ezekiel 22:12-13","1kings 21:13-16","james 5:4","isaiah 26:21","1kings 21:19","proverbs 1:19","ezekiel 22:6","genesis 4:12"],"40":["genesis 3:17-18","zephaniah 2:9","isaiah 7:23","psalms 72:20","malachi 1:3"]}