{"1":["genesis 12:6","judges 6:32","joshua 3:1","ecclesiastes 9:10","joshua 6:12","deuteronomy 11:30","genesis 22:3"],"2":["habakkuk 1:16","daniel 4:30","isaiah 2:11","zechariah 12:7","isaiah 2:17","zechariah 4:6","1corinthians 2:4-5","2corinthians 4:7","deuteronomy 8:17","jeremiah 9:23","ezekiel 28:17","2chronicles 14:11","1corinthians 1:27-29","romans 3:27","romans 11:18","2corinthians 10:4-5","1samuel 14:6","deuteronomy 32:27","isaiah 10:13","james 4:6","ephesians 2:9","ezekiel 28:2"],"3":["matthew 20:16","luke 14:25-33","deuteronomy 20:8","matthew 13:21","revelation 17:14","revelation 21:8"],"4":["psalms 66:10","malachi 3:2-3","1samuel 14:6","job 23:10","psalms 33:16","genesis 22:1","1samuel 16:7","psalms 7:9","jeremiah 6:27-30"],"7":["judges 7:18-22","1samuel 14:6","isaiah 41:14-16"],"8":["leviticus 25:9","joshua 6:4","isaiah 27:13","1corinthians 15:52","judges 3:27","numbers 10:9","joshua 6:20","judges 6:33","leviticus 23:24"],"9":["acts 27:23","joshua 1:5-9","2chronicles 20:17","acts 18:9-10","isaiah 43:1-2","matthew 2:13","judges 3:10","genesis 46:2-3","job 33:15-16","matthew 1:20","joshua 11:6","isaiah 41:10-16","2chronicles 16:8-9","joshua 10:8","judges 4:14-15","judges 3:28","joshua 2:24","job 4:13"],"10":["exodus 4:10-14","judges 4:8-9"],"11":["nehemiah 6:9","1samuel 23:16","philippians 4:13","ezra 6:22","judges 7:13-15","isaiah 35:3-4","exodus 13:18","ephesians 6:10","1samuel 14:8-10","genesis 24:14","2corinthians 12:9-10","ephesians 3:16","1samuel 14:12"],"12":["1kings 4:30","judges 6:3","isaiah 8:9-10","judges 6:33","2chronicles 14:9-12","psalms 3:1","judges 8:10","joshua 11:4","judges 6:5","psalms 33:16","psalms 118:10-12"],"13":["judges 3:31","1corinthians 1:27","isaiah 41:14-15","judges 4:21","judges 3:15","judges 6:15","judges 4:9"],"14":["numbers 22:38","job 1:10","joshua 5:1","joshua 2:9","2kings 7:6-7","joshua 2:24","exodus 15:14-15","numbers 23:20","numbers 24:10-13","numbers 23:5"],"15":["judges 4:14","genesis 40:8","exodus 4:30-31","genesis 24:48","2corinthians 10:4-6","2chronicles 20:18-19","genesis 41:11","genesis 24:26-27"],"16":["2corinthians 4:7"],"17":["judges 9:48","matthew 16:24","1peter 5:3","hebrews 13:7","1corinthians 11:1"],"18":["1samuel 17:47","2chronicles 20:15-17"],"19":["psalms 2:9","jeremiah 13:13-14","revelation 16:15","jeremiah 19:1-11","exodus 14:24","1thessalonians 5:2","judges 7:16","matthew 25:6"],"20":["hebrews 11:4","2corinthians 4:7","1thessalonians 4:16","joshua 6:4","2peter 1:15","isaiah 27:13","1corinthians 15:52","joshua 6:20","numbers 10:1-10","joshua 6:16"],"21":["exodus 14:25","2chronicles 20:17","2kings 7:6-7","job 15:21-22","exodus 14:13-14","isaiah 30:7","proverbs 28:1","isaiah 30:15"],"22":["joshua 6:4","psalms 83:9","isaiah 9:4","1samuel 14:16-20","2corinthians 4:7","isaiah 19:2","2chronicles 20:23","1kings 4:12","joshua 6:16","1kings 19:16","joshua 6:20"],"23":["1samuel 14:21-22","judges 6:35"],"24":["john 1:28","judges 12:5","judges 3:27-28","romans 15:30","philippians 1:27"],"25":["joshua 7:26","isaiah 10:26","judges 8:3-4","psalms 83:11-12"]}