{"1":["acts 2:6","esther 8:9","romans 1:7","1chronicles 12:18","daniel 6:25","ezra 4:17","ephesians 1:2","1peter 1:2","zechariah 8:23","daniel 3:4","1timothy 1:2","daniel 7:14","esther 3:12","daniel 3:29","daniel 6:27","ezra 5:7"],"2":["daniel 3:26","psalms 92:1-2","joshua 7:19","psalms 51:14","acts 22:3-16","acts 26:9-16","psalms 71:18","psalms 66:16"],"3":["psalms 145:13","romans 11:33","psalms 71:19-20","luke 1:32-33","daniel 6:26-27","isaiah 28:29","hebrews 1:8","1peter 4:11","isaiah 9:7","daniel 7:27","psalms 72:18","daniel 2:44","daniel 4:34-35","revelation 11:15","hebrews 2:4","jeremiah 10:10","1timothy 1:17","psalms 104:24","psalms 86:10","psalms 105:27","daniel 7:14","deuteronomy 4:34","daniel 4:17","psalms 66:7","psalms 92:5","job 25:2","isaiah 25:1","psalms 77:19"],"4":["ezekiel 28:2-5","isaiah 47:7-8","1thessalonians 5:2-3","isaiah 56:12","zephaniah 1:12","jeremiah 48:11","psalms 30:6-7","ezekiel 28:17","luke 12:19-20","ezekiel 29:3"],"5":["daniel 5:10","genesis 41:1","daniel 2:28-29","job 7:13-14","daniel 7:28","daniel 5:5-6","daniel 2:1"],"6":["genesis 41:7-8","isaiah 47:12-14","isaiah 8:19","daniel 2:2"],"7":["daniel 2:7","genesis 41:8","isaiah 44:25","daniel 2:10","2timothy 3:8-9","daniel 2:27","jeremiah 27:9-10","daniel 2:1-2"],"8":["numbers 11:17-30","daniel 4:9","jeremiah 50:2","isaiah 46:1","isaiah 63:11","daniel 5:11-12","daniel 1:7","daniel 4:18","daniel 2:11","daniel 5:14"],"9":["daniel 2:3-5","1samuel 4:8","isaiah 33:18","daniel 4:5","daniel 4:18","genesis 40:9-19","genesis 11:6-8","judges 7:13-15","daniel 4:8","genesis 41:38","ezekiel 28:3","daniel 5:11","isaiah 54:14","daniel 1:20","daniel 2:48","genesis 41:15-36"],"10":["daniel 4:20-26","isaiah 10:33-34","jeremiah 12:2","daniel 4:5","psalms 37:35-36","ezekiel 31:3-18"],"11":["deuteronomy 9:1","matthew 11:23","genesis 11:4","daniel 4:21-22"],"12":["ezekiel 31:6-7","matthew 13:32","lamentations 4:20","luke 13:19","ezekiel 17:23","mark 13:32","jeremiah 27:6-7"],"13":["mark 1:24","daniel 7:17","jude 1:14","deuteronomy 33:2","daniel 4:10","daniel 4:5","revelation 14:10","daniel 7:1","matthew 25:31","daniel 8:13","daniel 7:23","psalms 103:20","psalms 89:7","luke 4:34","daniel 4:23","zechariah 14:5"],"14":["daniel 4:12","daniel 4:23","jeremiah 51:9","matthew 3:10","revelation 18:2","daniel 3:4","ezekiel 31:12-13","matthew 7:19","daniel 5:20","revelation 10:3","luke 13:7-9","luke 3:9","jeremiah 51:6"],"15":["job 14:7-9","daniel 4:25-27","ezekiel 29:14-15"],"16":["luke 8:27-29","daniel 7:25","daniel 4:23","daniel 4:25","daniel 4:31-33","daniel 12:7","daniel 11:13","mark 5:4-5","isaiah 6:10","revelation 12:14","hebrews 1:11"],"17":["2kings 21:6-18","psalms 12:8","1corinthians 1:28","ezekiel 25:17","daniel 4:32-35","psalms 113:7-8","daniel 11:21","ezekiel 7:24","psalms 75:6-7","isaiah 6:8","daniel 4:25","psalms 83:17-18","1kings 22:19-20","1samuel 2:8","daniel 5:18-21","exodus 9:16","1kings 21:25","1timothy 5:21","jeremiah 27:5-7","psalms 9:16","daniel 2:21","isaiah 6:3","daniel 4:13-14","daniel 4:8-9","2chronicles 28:22","revelation 4:8"],"18":["daniel 2:26-28","daniel 4:7-9","amos 3:7","isaiah 47:12-14","daniel 5:8","isaiah 19:3","genesis 41:15","daniel 2:7","1kings 14:2-3","daniel 5:15","genesis 41:8"],"19":["2samuel 18:31-32","1samuel 3:17","1samuel 24:8","jeremiah 29:7","1kings 18:7","1samuel 1:15","daniel 4:24","genesis 32:4-5","daniel 2:26","jeremiah 4:19","exodus 32:32","daniel 8:27","1samuel 26:15","daniel 10:16-17","daniel 4:8-9","genesis 31:35","genesis 32:18","daniel 7:15","daniel 4:4-5","habakkuk 3:10","daniel 5:12","daniel 7:28","daniel 1:7"],"20":["daniel 4:10-12","ezekiel 31:3","ezekiel 31:16"],"22":["psalms 108:4","jeremiah 27:6-8","2chronicles 28:9","daniel 5:18-23","psalms 36:5","daniel 2:37-38","2samuel 12:7","genesis 11:4","matthew 14:4","revelation 18:5","genesis 28:12"],"23":["daniel 5:21","daniel 4:13-16"],"24":["isaiah 14:24-27","isaiah 23:9","job 20:29","psalms 148:6","job 1:12-19","job 40:11-12","daniel 4:17","isaiah 46:10-11","psalms 2:7","psalms 107:40"],"25":["daniel 4:17","psalms 106:20","psalms 75:7","mark 5:3-4","psalms 83:18","daniel 2:21","jeremiah 27:5","daniel 5:21-31","daniel 4:32-35","job 30:3-8"],"26":["daniel 4:23","daniel 2:37","luke 15:18","luke 15:21","matthew 21:20","daniel 4:15","matthew 5:34"],"27":["isaiah 58:10-12","job 34:31-32","acts 8:22","psalms 41:1-3","proverbs 16:6","psalms 119:46","ezekiel 18:7","luke 11:41","zephaniah 2:2-3","genesis 41:33-37","acts 10:2-4","proverbs 28:13","galatians 5:6","galatians 5:22","ezekiel 18:27-32","2corinthians 5:11","ephesians 4:28","isaiah 58:5-7","acts 24:25","acts 26:20","matthew 3:8","galatians 5:13","ezekiel 18:21-22","1peter 4:8","jonah 3:9","james 4:8-10","isaiah 55:6-7","joel 2:14","1kings 21:29"],"28":["zechariah 1:6","numbers 23:19","proverbs 10:24","matthew 24:35"],"29":["revelation 2:21","2peter 3:15","1peter 3:20","ecclesiastes 8:11","2peter 3:9-10","genesis 6:3"],"30":["1corinthians 10:31","psalms 104:1","revelation 18:10","habakkuk 1:15-16","revelation 16:19","psalms 73:8","ezekiel 29:3","psalms 49:20","habakkuk 2:4-5","luke 12:19-20","isaiah 10:8-15","esther 1:4","1chronicles 29:12-14","2chronicles 2:5-6","revelation 17:5","daniel 5:18-20","ezekiel 28:2-5","revelation 18:21","luke 14:11","psalms 145:5-12","genesis 11:2-9","1peter 5:5","genesis 10:10","isaiah 37:24-25","revelation 21:24-26","proverbs 16:18"],"31":["matthew 3:17","1samuel 15:23","exodus 15:9-10","luke 12:20","daniel 5:28","acts 9:3-5","daniel 4:24","job 20:23","daniel 5:4-5","acts 12:22-23","revelation 16:7","john 12:28","daniel 4:34","1samuel 13:14","1thessalonians 5:3"],"32":["daniel 4:14-17","exodus 8:10","isaiah 37:20","job 12:18-21","isaiah 45:3","job 30:5-7","exodus 9:14","joshua 4:24","proverbs 8:15-16","jeremiah 27:5","daniel 4:25-26","exodus 9:29","daniel 5:21"],"33":["daniel 4:32","daniel 5:21","job 20:5","daniel 4:25","isaiah 30:14","daniel 5:5","1thessalonians 5:2"],"34":["psalms 50:14","luke 18:13","john 5:26","psalms 90:1-2","psalms 7:17","1timothy 6:16","daniel 6:26","daniel 5:21","job 1:21","psalms 9:2","isaiah 24:15","psalms 107:15","daniel 12:7","psalms 10:16","lamentations 3:38","revelation 10:6","1timothy 1:17","jeremiah 10:10","revelation 11:15","psalms 107:22","psalms 92:1","daniel 7:14","daniel 4:32","daniel 2:44","revelation 4:10","micah 4:7","daniel 4:3","psalms 107:8","psalms 146:10","jonah 2:2-4","psalms 121:1","psalms 130:1-2","daniel 4:26","lamentations 3:19-23","psalms 103:1-4","psalms 123:1","psalms 145:13","daniel 4:16-17","luke 1:33","psalms 102:24","isaiah 9:6-7","psalms 107:31"],"35":["job 34:29","job 42:2","job 40:9-12","job 9:12-13","philippians 2:10-11","matthew 11:25-26","isaiah 43:13","job 23:13","isaiah 14:24-27","isaiah 45:9-11","acts 5:39","job 33:12-13","job 34:19-24","isaiah 26:9","acts 4:28","isaiah 46:10-11","psalms 49:1","job 40:2","job 34:14-15","psalms 33:8-11","ephesians 1:11","psalms 33:14","acts 11:17","proverbs 21:30","1samuel 3:18","1corinthians 10:22","isaiah 40:22-24","romans 11:33-36","psalms 135:6","psalms 115:3","1corinthians 2:16","job 9:4","romans 9:19-20","acts 9:5","isaiah 40:15-17"],"36":["1samuel 2:30","2corinthians 4:17","daniel 4:32","daniel 4:15-16","2chronicles 33:12-13","job 13:12","daniel 4:34","proverbs 22:4","matthew 6:33"],"37":["2chronicles 33:11-12","revelation 16:7","psalms 33:4-5","job 40:11-12","acts 17:24","ezekiel 16:56","revelation 19:1-2","revelation 15:3","ezekiel 16:63","1peter 5:5-6","daniel 4:34","daniel 5:4","psalms 145:17-18","matthew 11:25","psalms 119:75","daniel 4:30-31","daniel 4:3","2chronicles 33:19","isaiah 5:16","james 4:6-7","deuteronomy 32:4","exodus 18:11","1samuel 2:3","daniel 5:20-24","1peter 2:9-10","psalms 99:4"]}