{"1":["numbers 34:17-29"],"2":["numbers 26:55-56","proverbs 18:18","matthew 25:34","numbers 34:13","numbers 33:54","psalms 16:5-6","proverbs 16:33"],"3":["joshua 13:32-33","deuteronomy 3:12-17","joshua 13:8","joshua 13:14","numbers 32:29-42"],"4":["genesis 48:5","numbers 35:2-8","1chronicles 6:54-81","1chronicles 5:1-2","joshua 21:2-42"],"5":["numbers 35:1-2","joshua 21:2"],"6":["numbers 13:26","numbers 14:6","joshua 15:17","deuteronomy 34:10","numbers 14:24","2kings 8:11","1kings 13:14","deuteronomy 33:1","psalms 90:1","numbers 13:6","2kings 4:16","deuteronomy 1:36-38","2kings 8:7","1kings 13:1","1timothy 6:11","joshua 14:14","2kings 4:42","2timothy 3:17","numbers 32:12","deuteronomy 34:5","numbers 12:7-8","joshua 4:19","2kings 4:9","judges 13:6-8","joshua 10:43","numbers 14:30"],"7":["numbers 13:6","numbers 14:6-10","numbers 13:26-33","numbers 13:16-20"],"8":["numbers 14:24","revelation 14:4","numbers 13:31","joshua 14:14","deuteronomy 1:36"],"9":["numbers 13:22","deuteronomy 1:36","joshua 1:3","numbers 14:22-24"],"10":["joshua 11:18","numbers 14:30","numbers 14:33-34"],"11":["psalms 103:5","deuteronomy 31:2","deuteronomy 34:7","psalms 90:10"],"12":["psalms 118:10-12","psalms 18:32-34","hebrews 11:33","numbers 13:28","joshua 11:21-22","1samuel 14:6","psalms 60:12","numbers 21:34","numbers 14:8-9","romans 8:31","2chronicles 14:11","psalms 44:3","joshua 15:14","philippians 4:13","judges 1:20","psalms 27:1-3","numbers 13:33"],"13":["judges 1:20","joshua 10:36-37","genesis 47:10","joshua 15:13","songofsolomon 6:9","joshua 22:6","joshua 21:11-12","1chronicles 6:55-56","1samuel 1:17","genesis 47:7"],"14":["1corinthians 15:58","joshua 14:8-9"],"15":["judges 5:31","judges 3:11","genesis 23:2","joshua 15:13","judges 8:28","joshua 11:23","judges 3:30"]}